Workbook

Sheet Start here
A1: LisheBora pilot test – Makueni County, Kalulini school (demo data)
A2: Purpose: AATF staff test every process end to end with demo accounts before real users are invited. All figures are illustrative.
A4: Before you start
A5: 1. On the LisheBora computer run scripts\use-demo.bat (demo database), then scripts\start-test-server.bat. Three windows open (API, worker, website); keep them open and the computer awake.
A6: 2. The start window shows the address to share, e.g. http://192.168.x.x:3000. Testers on the same office network open it in their browser. Staff sign in at /sign-in; administrators at /admin/sign-in.
A7: 3. Every demo account uses the password: Demo!2026pass
A8: 4. Some roles ask for a 6-digit code. In demo mode the code is shown on the screen (no SMS is sent).
A9: 5. Use a separate browser (or a private window) per person so sessions do not mix; or sign out between roles.
A10: 6. The sourcing event must close more than 1 hour after it is submitted. Do stages 13 and 15 while you wait.
A11: 7. Fill the Result column (Pass / Fail / Blocked) and write what you saw in Comments. Log problems on the Issues sheet with a screenshot.
A13: What is in the demo data
A14: Real Makueni, Embu and Isiolo schools; demo accounts for every role in Makueni; two prequalified demo suppliers (Umoja cooperative, Tumaini traders); an Umoja aggregation hub and a county food store; illustrative reference prices; one older demo order (PO-DEMO-0001) for Kalulini and Muatini.
... A20: Rows marked ‘Control’ check that the system REFUSES something (e.g. approving your own request). A control passes when the action is blocked.

Sheet Accounts
A1: Email (sign-in) | B1: Role | C1: Area | D1: Sign-in page | E1: Used for | F1: Password
A2: admin@lishebora.local | B2: Super Administrator | C2: National | D2: /admin/sign-in | E2: Features & menus, administrator accounts (password ChangeMe!2026) | F2: ChangeMe!2026
A3: administrator@demo.lishebora | B3: Administrator | C3: National | D3: /admin/sign-in | E3: Readiness checklist, users, master data, website publishing | F3: Demo!2026pass
A4: editor@demo.lishebora | B4: Content Editor | C4: National | D4: /sign-in | E4: Drafts website news and pages (cannot publish) | F4: Demo!2026pass
A5: nutrition@demo.lishebora | B5: Nutrition Officer | C5: Makueni County | D5: /sign-in | E5: Creates the term menu | F5: Demo!2026pass
A6: procurement@demo.lishebora | B6: County Procurement Officer | C6: Makueni County | D6: /sign-in | E6: Approves menus, builds the plan, vets suppliers, runs sourcing | F6: Demo!2026pass
A7: meals.officer@demo.lishebora | B7: School Meals Officer | C7: Kalulini school | D7: /sign-in | E7: School demand, daily food use | F7: Demo!2026pass
A8: school.admin@demo.lishebora | B8: School Administrator | C8: Kalulini school | D8: /sign-in | E8: Approves demand, school GPS, confirms deliveries, complaints | F8: Demo!2026pass
A9: finance@demo.lishebora | B9: County Finance Officer | C9: Makueni County | D9: /sign-in | E9: Budget lines, budget confirmation, invoice approval | F9: Demo!2026pass
A10: county.admin@demo.lishebora | B10: County Administrator | C10: Makueni County | D10: /sign-in | E10: Approves plans, prequalifies suppliers, resolves cases | F10: Demo!2026pass
A11: approver@demo.lishebora | B11: Approving Officer | C11: Makueni County | D11: /sign-in | E11: Approves sourcing events and awards | F11: Demo!2026pass
A12: evaluator1@demo.lishebora | B12: Evaluation Committee Member 1 | C12: Makueni County | D12: /sign-in | E12: Declares conflict of interest, scores bids | F12: Demo!2026pass
... A29: (registers on the website) | B29: New supplier – your own test farmer group | C29: Own organisation | D29: /register | E29: Self-registration, documents, bidding | F29: choose your own

Sheet Test script
A1: # | B1: Stage | C1: Step | D1: Type | E1: Who | F1: Account | G1: Where in the system | H1: What to do | I1: Expected result | J1: Result | K1: Tester | L1: Date | M1: Comments
A2: 1 | B2: 1 Set-up | C2: Sign in as administrator | D2: Process | E2: Administrator | F2: administrator@demo.lishebora | G2: /admin/sign-in | H2: Sign in with the password, then type the 6-digit code shown on the screen (demo mode). | I2: The admin console opens.
A3: 2 | B3: 1 Set-up | C3: Administrator cannot use the staff sign-in | D3: Control | E3: Administrator | F3: administrator@demo.lishebora | G3: /sign-in | H3: Try the administrator email on the normal sign-in page. | I3: Refused with a message to use the administration sign-in.
A4: 3 | B4: 1 Set-up | C4: Check pilot readiness | D4: Process | E4: Administrator | F4: administrator@demo.lishebora | G4: Administration › Pilot readiness | H4: Open the page and read the items. | I4: The checklist loads with a percentage and Fix links (demo data is flagged – expected for this test).
A5: 4 | B5: 1 Set-up | C5: Record the school's location | D5: Process | E5: School Administrator | F5: school.admin@demo.lishebora | G5: Plan › School locations | H5: Open Kalulini › Set location. On a phone at the school tap ‘Use my location’; otherwise click the school on the map or type the coordinates. Save. | I5: Coordinates saved with ‘how captured’, your name and time.
A6: 5 | B6: 1 Set-up | C6: Wrong coordinates are refused | D6: Control | E6: School Administrator | F6: school.admin@demo.lishebora | G6: Plan › School locations | H6: Type latitude 37.62 and longitude -1.80 (swapped) and save. | I6: Refused: ‘outside Kenya … not swapped’.
A7: 6 | B7: 2 Menu | C7: Create the term menu | D7: Process | E7: Nutrition Officer | F7: nutrition@demo.lishebora | G7: Plan › Menus & terms | H7: New menu: 5 days (Mon–Fri) with dishes and portions in grams (e.g. ugali, beans, sukuma wiki, oil, salt). | I7: Menu saved as draft; the food-group summary shows whether it meets the diversity minimum.
A8: 7 | B8: 2 Menu | C8: Submit the menu | D8: Process | E8: Nutrition Officer | F8: nutrition@demo.lishebora | G8: Plan › Menus & terms | H8: Submit the menu for validation. | I8: Status ‘submitted’; appears in the procurement officer’s ‘My approvals’.
A9: 8 | B9: 2 Menu | C9: Cannot approve own menu | D9: Control | E9: Nutrition Officer | F9: nutrition@demo.lishebora | G9: Overview › My approvals | H9: Look for an approve button on your own menu. | I9: Not available / refused.
A10: 9 | B10: 2 Menu | C10: Return needs a reason | D10: Control | E10: County Procurement Officer | F10: procurement@demo.lishebora | G10: Overview › My approvals | H10: Choose ‘Return’ without typing a reason. | I10: Refused until a reason is given.
A11: 10 | B11: 2 Menu | C11: Approve the menu | D11: Process | E11: County Procurement Officer | F11: procurement@demo.lishebora | G11: Overview › My approvals | H11: Approve the menu. | I11: Menu status ‘approved’; it can now be chosen for school demand.
A12: 11 | B12: 3 School demand | C12: Record school demand | D12: Process | E12: School Meals Officer | F12: meals.officer@demo.lishebora | G12: Plan › School demand | H12: New demand for Kalulini, Term 3 2026, the approved menu. Learners (pre-filled from enrolment, adjust if needed), attendance 95 %, 40 feeding days, wastage 3 %, food already in stock. | I12: Quantities per food item are calculated; no red (blocking) flags.
A13: 12 | B13: 3 School demand | C13: Too many feeding days is blocked | D13: Control | E13: School Meals Officer | F13: meals.officer@demo.lishebora | G13: Plan › School demand | H13: Change feeding days to 120 and try to submit. | I13: Flag ‘feeding days’ and submission refused. Set it back to 40.
... A90: 89 | B90: 16 Menus & access | C90: Administrator cannot change menus | D90: Control | E90: Administrator | F90: administrator@demo.lishebora | G90: Administration | H90: As administrator@demo.lishebora look for Features & menus. | I90: Not in the menu (Super Administrator only).

Sheet Progress
A1: Stage | B1: Steps | C1: Pass | D1: Fail | E1: Blocked | F1: Not done
A2: 1 Set-up | B2: =COUNTIF('Test script'!B2:B90,A2) | C2: =COUNTIFS('Test script'!B2:B90,A2,'Test script'!J2:J90,"Pass") | D2: =COUNTIFS('Test script'!B2:B90,A2,'Test script'!J2:J90,"Fail") | E2: =COUNTIFS('Test script'!B2:B90,A2,'Test script'!J2:J90,"Blocked") | F2: =B2-C2-D2-E2
A3: 2 Menu | B3: =COUNTIF('Test script'!B2:B90,A3) | C3: =COUNTIFS('Test script'!B2:B90,A3,'Test script'!J2:J90,"Pass") | D3: =COUNTIFS('Test script'!B2:B90,A3,'Test script'!J2:J90,"Fail") | E3: =COUNTIFS('Test script'!B2:B90,A3,'Test script'!J2:J90,"Blocked") | F3: =B3-C3-D3-E3
A4: 3 School demand | B4: =COUNTIF('Test script'!B2:B90,A4) | C4: =COUNTIFS('Test script'!B2:B90,A4,'Test script'!J2:J90,"Pass") | D4: =COUNTIFS('Test script'!B2:B90,A4,'Test script'!J2:J90,"Fail") | E4: =COUNTIFS('Test script'!B2:B90,A4,'Test script'!J2:J90,"Blocked") | F4: =B4-C4-D4-E4
A5: 4 Budget & plan | B5: =COUNTIF('Test script'!B2:B90,A5) | C5: =COUNTIFS('Test script'!B2:B90,A5,'Test script'!J2:J90,"Pass") | D5: =COUNTIFS('Test script'!B2:B90,A5,'Test script'!J2:J90,"Fail") | E5: =COUNTIFS('Test script'!B2:B90,A5,'Test script'!J2:J90,"Blocked") | F5: =B5-C5-D5-E5
A6: 5 Supplier onboarding | B6: =COUNTIF('Test script'!B2:B90,A6) | C6: =COUNTIFS('Test script'!B2:B90,A6,'Test script'!J2:J90,"Pass") | D6: =COUNTIFS('Test script'!B2:B90,A6,'Test script'!J2:J90,"Fail") | E6: =COUNTIFS('Test script'!B2:B90,A6,'Test script'!J2:J90,"Blocked") | F6: =B6-C6-D6-E6
A7: 6 Sourcing | B7: =COUNTIF('Test script'!B2:B90,A7) | C7: =COUNTIFS('Test script'!B2:B90,A7,'Test script'!J2:J90,"Pass") | D7: =COUNTIFS('Test script'!B2:B90,A7,'Test script'!J2:J90,"Fail") | E7: =COUNTIFS('Test script'!B2:B90,A7,'Test script'!J2:J90,"Blocked") | F7: =B7-C7-D7-E7
A8: 7 Contract & order | B8: =COUNTIF('Test script'!B2:B90,A8) | C8: =COUNTIFS('Test script'!B2:B90,A8,'Test script'!J2:J90,"Pass") | D8: =COUNTIFS('Test script'!B2:B90,A8,'Test script'!J2:J90,"Fail") | E8: =COUNTIFS('Test script'!B2:B90,A8,'Test script'!J2:J90,"Blocked") | F8: =B8-C8-D8-E8
A9: 8 Aggregation & quality | B9: =COUNTIF('Test script'!B2:B90,A9) | C9: =COUNTIFS('Test script'!B2:B90,A9,'Test script'!J2:J90,"Pass") | D9: =COUNTIFS('Test script'!B2:B90,A9,'Test script'!J2:J90,"Fail") | E9: =COUNTIFS('Test script'!B2:B90,A9,'Test script'!J2:J90,"Blocked") | F9: =B9-C9-D9-E9
A10: 9 Warehouse | B10: =COUNTIF('Test script'!B2:B90,A10) | C10: =COUNTIFS('Test script'!B2:B90,A10,'Test script'!J2:J90,"Pass") | D10: =COUNTIFS('Test script'!B2:B90,A10,'Test script'!J2:J90,"Fail") | E10: =COUNTIFS('Test script'!B2:B90,A10,'Test script'!J2:J90,"Blocked") | F10: =B10-C10-D10-E10
A11: 10 Dispatch & delivery | B11: =COUNTIF('Test script'!B2:B90,A11) | C11: =COUNTIFS('Test script'!B2:B90,A11,'Test script'!J2:J90,"Pass") | D11: =COUNTIFS('Test script'!B2:B90,A11,'Test script'!J2:J90,"Fail") | E11: =COUNTIFS('Test script'!B2:B90,A11,'Test script'!J2:J90,"Blocked") | F11: =B11-C11-D11-E11
A12: 11 School stock | B12: =COUNTIF('Test script'!B2:B90,A12) | C12: =COUNTIFS('Test script'!B2:B90,A12,'Test script'!J2:J90,"Pass") | D12: =COUNTIFS('Test script'!B2:B90,A12,'Test script'!J2:J90,"Fail") | E12: =COUNTIFS('Test script'!B2:B90,A12,'Test script'!J2:J90,"Blocked") | F12: =B12-C12-D12-E12
A13: 12 Invoice & payment | B13: =COUNTIF('Test script'!B2:B90,A13) | C13: =COUNTIFS('Test script'!B2:B90,A13,'Test script'!J2:J90,"Pass") | D13: =COUNTIFS('Test script'!B2:B90,A13,'Test script'!J2:J90,"Fail") | E13: =COUNTIFS('Test script'!B2:B90,A13,'Test script'!J2:J90,"Blocked") | F13: =B13-C13-D13-E13
A14: 13 Complaints & recall | B14: =COUNTIF('Test script'!B2:B90,A14) | C14: =COUNTIFS('Test script'!B2:B90,A14,'Test script'!J2:J90,"Pass") | D14: =COUNTIFS('Test script'!B2:B90,A14,'Test script'!J2:J90,"Fail") | E14: =COUNTIFS('Test script'!B2:B90,A14,'Test script'!J2:J90,"Blocked") | F14: =B14-C14-D14-E14
A15: 14 Monitoring & audit | B15: =COUNTIF('Test script'!B2:B90,A15) | C15: =COUNTIFS('Test script'!B2:B90,A15,'Test script'!J2:J90,"Pass") | D15: =COUNTIFS('Test script'!B2:B90,A15,'Test script'!J2:J90,"Fail") | E15: =COUNTIFS('Test script'!B2:B90,A15,'Test script'!J2:J90,"Blocked") | F15: =B15-C15-D15-E15
A16: 15 Website content | B16: =COUNTIF('Test script'!B2:B90,A16) | C16: =COUNTIFS('Test script'!B2:B90,A16,'Test script'!J2:J90,"Pass") | D16: =COUNTIFS('Test script'!B2:B90,A16,'Test script'!J2:J90,"Fail") | E16: =COUNTIFS('Test script'!B2:B90,A16,'Test script'!J2:J90,"Blocked") | F16: =B16-C16-D16-E16
A17: 16 Menus & access | B17: =COUNTIF('Test script'!B2:B90,A17) | C17: =COUNTIFS('Test script'!B2:B90,A17,'Test script'!J2:J90,"Pass") | D17: =COUNTIFS('Test script'!B2:B90,A17,'Test script'!J2:J90,"Fail") | E17: =COUNTIFS('Test script'!B2:B90,A17,'Test script'!J2:J90,"Blocked") | F17: =B17-C17-D17-E17
A18: Total | B18: =SUM(B2:B17) | C18: =SUM(C2:C17) | D18: =SUM(D2:D17) | E18: =SUM(E2:E17) | F18: =SUM(F2:F17)

Sheet Issues
A1: # | B1: Step # | C1: Found by | D1: Date | E1: What happened | F1: Expected | G1: Severity | H1: Screenshot / file | I1: Status | J1: Fixed in
A2: 1
A3: 2
A4: 3
A5: 4
A6: 5
A7: 6
A8: 7
A9: 8
A10: 9
A11: 10
A12: 11
A13: 12
... A59: 58
